netorca
tests
