Metadata-Version: 2.1
Name: netautomate.netorca
Version: 1.0.9
Summary: Ansible modules to interact with NetOrca
Author: Scott Rowlandson
Author-email: scott@netautomate.org
